aymara_ai/__init__.py
aymara_ai/client_config.yml
aymara_ai/types.py
aymara_ai/version.py
aymara_ai/core/__init__.py
aymara_ai/core/policies.py
aymara_ai/core/protocols.py
aymara_ai/core/score_runs.py
aymara_ai/core/sdk.py
aymara_ai/core/summaries.py
aymara_ai/core/tests.py
aymara_ai/core/uploads.py
aymara_ai/examples/__init__.py
aymara_ai/examples/demo_student.py
aymara_ai/examples/accuracy/accuracy_notebook.ipynb
aymara_ai/examples/accuracy/aymara_language.txt
aymara_ai/examples/accuracy/aymaratherium.txt
aymara_ai/examples/accuracy/bolivia.txt
aymara_ai/examples/jailbreak/__init__.py
aymara_ai/examples/jailbreak/jailbreak_notebook.ipynb
aymara_ai/examples/safety/__init__.py
aymara_ai/examples/safety/free_trial_notebook.ipynb
aymara_ai/examples/safety/text-to-image_safety_notebook.ipynb
aymara_ai/examples/safety/text-to-text_safety_notebook.ipynb
aymara_ai/generated/.gitignore
aymara_ai/generated/README.md
aymara_ai/generated/pyproject.toml
aymara_ai/generated/aymara_api_client/__init__.py
aymara_ai/generated/aymara_api_client/client.py
aymara_ai/generated/aymara_api_client/errors.py
aymara_ai/generated/aymara_api_client/py.typed
aymara_ai/generated/aymara_api_client/types.py
aymara_ai/generated/aymara_api_client/api/__init__.py
aymara_ai/generated/aymara_api_client/api/accounts/__init__.py
aymara_ai/generated/aymara_api_client/api/accounts/get_me.py
aymara_ai/generated/aymara_api_client/api/health/__init__.py
aymara_ai/generated/aymara_api_client/api/health/health_check.py
aymara_ai/generated/aymara_api_client/api/integration_test/__init__.py
aymara_ai/generated/aymara_api_client/api/integration_test/integration_test.py
aymara_ai/generated/aymara_api_client/api/policies/__init__.py
aymara_ai/generated/aymara_api_client/api/policies/list_policies.py
aymara_ai/generated/aymara_api_client/api/score_runs/__init__.py
aymara_ai/generated/aymara_api_client/api/score_runs/create_score_run.py
aymara_ai-0.8.5.dist-info/METADATA
aymara_ai-0.8.5.dist-info/WHEEL
aymara_ai-0.8.5.dist-info/licenses/LICENSE
aymara_ai-0.8.5.dist-info/RECORD
