Metadata-Version: 2.4
Name: aymara-ai
Version: 0.8.5
Summary: A Python SDK for using Aymara to test your AI alignment.
Project-URL: Homepage, https://www.aymara.ai/
Project-URL: Bug Tracker, https://github.com/aymara-ai/aymara-sdk/issues
Author-email: Aymara AI <support@aymara.ai>
License:                                  Apache License
License-File: LICENSE
Keywords: ai,alignment,testing
Classifier: Operating System :: OS Independent
Classifier: Programming Language :: Python :: 3
Requires-Python: >=3.9
Requires-Dist: boto3>=1.35.66
Requires-Dist: colorama>=0.4.6
Requires-Dist: httpx==0.27.2
Requires-Dist: ipykernel==6.29.5
Requires-Dist: ipywidgets==8.1.5
Requires-Dist: jupyter==1.1.0
Requires-Dist: matplotlib>=3.7.5
Requires-Dist: multiprocess==0.70.16
Requires-Dist: openai>=1.55.0
Requires-Dist: pandas>=1.5.0
Requires-Dist: pydantic<3.0.0,>=2.1.1
Requires-Dist: python-dotenv==1.0.1
Requires-Dist: requests==2.32.3
Requires-Dist: sphinxcontrib-googleanalytics>=0.4
Requires-Dist: tiktoken>=0.8.0
Requires-Dist: tqdm==4.66.5
Requires-Dist: uuid-utils==0.9.0
